tts_webui_extension/mms/__init__.py
tts_webui_extension/mms/main.py
tts_webui_extension/mms/resources/__init__.py
tts_webui_extension/mms/resources/mms-languages-iso639-3.txt
tts_webui_extension_mms-0.0.4.dist-info/licenses/LICENSE
tts_webui_extension_mms-0.0.4.dist-info/METADATA
tts_webui_extension_mms-0.0.4.dist-info/WHEEL
tts_webui_extension_mms-0.0.4.dist-info/top_level.txt
tts_webui_extension_mms-0.0.4.dist-info/RECORD
