Metadata-Version: 2.4
Name: tts_webui_extension.mms
Version: 0.0.4
Summary: MMS (Massively Multilingual Speech) is a text-to-speech model supporting over 1000 languages
Author: rsxdalv
Project-URL: Homepage, https://github.com/rsxdalv/tts_webui_extension.mms
Classifier: Programming Language :: Python :: 3
Classifier: License :: OSI Approved :: MIT License
Classifier: Operating System :: OS Independent
Requires-Python: >=3.7
License-File: LICENSE
Requires-Dist: transformers>=4.30.0
Requires-Dist: iso639-lang==2.2.3
Dynamic: license-file
